API/API.py
API/__init__.py
Interfaces/CataloguerInterface.py
Interfaces/IngestorInterface.py
Interfaces/ValidatorInterface.py
Interfaces/__init__.py
ParameterClasses/AuthInfo.py
ParameterClasses/AuthToken.py
ParameterClasses/DataSetId.py
ParameterClasses/Schema.py
ParameterClasses/__init__.py
Tools/Cataloguer.py
Tools/Importer.py
Tools/Ingestor.py
Tools/Validator.py
Tools/__init__.py
aep_sdk/API.py
aep_sdk/__init__.py
aep_sdk/Interfaces/CataloguerInterface.py
aep_sdk/Interfaces/IngestorInterface.py
aep_sdk/Interfaces/ValidatorInterface.py
aep_sdk/Interfaces/__init__.py
aep_sdk/ParameterClasses/AuthInfo.py
aep_sdk/ParameterClasses/AuthToken.py
aep_sdk/ParameterClasses/DataSetId.py
aep_sdk/ParameterClasses/Schema.py
aep_sdk/ParameterClasses/__init__.py
aep_sdk/Tests/__init__.py
aep_sdk/Tests/test.py
aep_sdk/Tools/Cataloguer.py
aep_sdk/Tools/Importer.py
aep_sdk/Tools/Ingestor.py
aep_sdk/Tools/Validator.py
aep_sdk/Tools/__init__.py
aep_sdk-0.0.35.dist-info/LICENSE
aep_sdk-0.0.35.dist-info/METADATA
aep_sdk-0.0.35.dist-info/WHEEL
aep_sdk-0.0.35.dist-info/top_level.txt
aep_sdk-0.0.35.dist-info/RECORD
