Metadata-Version: 2.1
Name: aep-sdk
Version: 0.0.35
Summary: A SDK for the Adobe Experience Platform
Home-page: https://github.com/Dacson33/Experience-Platform-Python-SDK/
Author: ['Dakoda Richardson', 'Benson Condie', 'Adam Ure', 'Nick Cummings', 'Lance Haderlie']
License: UNKNOWN
Platform: UNKNOWN
Classifier: Programming Language :: Python
Classifier: Programming Language :: Python :: 3
Classifier: Operating System :: OS Independent
Classifier: Topic :: Utilities
Classifier: License :: OSI Approved :: MIT License
Requires-Python: >=3.7
Requires-Dist: requests
Requires-Dist: PyJWT
Requires-Dist: bitmath
Requires-Dist: cryptography
